society_elections/__init__.py
society_elections/app_settings.py
society_elections/apps.py
society_elections/decorators.py
society_elections/tests.py
society_elections/urls.py
society_elections/validators.py
society_elections/admin/__init__.py
society_elections/admin/candidate.py
society_elections/admin/decorators.py
society_elections/admin/election.py
society_elections/admin/electionposition.py
society_elections/admin/position.py
society_elections/admin/voter.py
society_elections/forms/__init__.py
society_elections/forms/candidate.py
society_elections/forms/election.py
society_elections/forms/voter.py
society_elections/migrations/0001_initial.py
society_elections/migrations/0002_auto_20211001_2101.py
society_elections/migrations/0003_candidate_manifesto.py
society_elections/migrations/0004_remove_voter_email_salt.py
society_elections/migrations/0005_auto_20211021_2126.py
society_elections/migrations/0006_auto_20211101_1735.py
society_elections/migrations/0007_auto_20211101_1815.py
society_elections/migrations/0008_auto_20211113_1111.py
society_elections/migrations/__init__.py
society_elections/models/__init__.py
society_elections/models/candidate.py
society_elections/models/election.py
society_elections/models/electionposition.py
society_elections/models/position.py
society_elections/models/vote.py
society_elections/models/voter.py
society_elections/templates/society_elections/election_wrong_period.html
society_elections/templates/society_elections/password_entry.html
society_elections/templates/society_elections/vote.html
society_elections/templates/society_elections/vote_submitted.html
society_elections/templates/society_elections/voter_404.html
society_elections/templates/society_elections/voter_not_verified.html
society_elections/tests/__init__.py
society_elections/tests/helpers.py
society_elections/tests/views_helper.py
society_elections/tests/views_vote.py
society_elections/tests/views_voter.py
society_elections/views/__init__.py
django_society_elections-0.0.15.dist-info/LICENSE
django_society_elections-0.0.15.dist-info/METADATA
django_society_elections-0.0.15.dist-info/WHEEL
django_society_elections-0.0.15.dist-info/top_level.txt
django_society_elections-0.0.15.dist-info/RECORD
